cavcalc/__init__.py
cavcalc/__main__.py
cavcalc/__version__.py
cavcalc/_arguments/__init__.py
cavcalc/_arguments/_container.py
cavcalc/_arguments/_groups.py
cavcalc/_arguments/_types.py
cavcalc/_arguments/_utils.py
cavcalc/_default.mplstyle
cavcalc/_exiters.py
cavcalc/_handler.py
cavcalc/_main.py
cavcalc/_session.py
cavcalc/calculate.py
cavcalc/cavcalc.ini
cavcalc/env.py
cavcalc/errors.py
cavcalc/functions/__init__.py
cavcalc/functions/_maps.py
cavcalc/functions/_utils.py
cavcalc/functions/asymmetric.py
cavcalc/functions/resonance.py
cavcalc/functions/symmetric.py
cavcalc/output.py
cavcalc/parameters/__init__.py
cavcalc/parameters/_maps.py
cavcalc/parameters/enums.py
cavcalc/parameters/parameter.py
cavcalc/parameters/tools.py
cavcalc/testing.py
cavcalc-1.3.0.dist-info/LICENSE
cavcalc-1.3.0.dist-info/METADATA
cavcalc-1.3.0.dist-info/WHEEL
cavcalc-1.3.0.dist-info/entry_points.txt
cavcalc-1.3.0.dist-info/RECORD
