Metadata-Version: 2.1
Name: cavcalc
Version: 1.3.0
Summary: A program for computing Fabry-Perot optical cavity parameters.
Home-page: https://cavcalc.readthedocs.io/en/latest/
License: GPL-3.0-or-later
Keywords: physics,optics,interferometry
Author: Samuel Rowlinson
Author-email: samueljrowlinson@gmail.com
Requires-Python: >=3.9,<4.0
Classifier: Development Status :: 4 - Beta
Classifier: Intended Audience :: Science/Research
Classifier: License :: OSI Approved :: GNU General Public License v3 or later (GPLv3+)
Classifier: Programming Language :: Python :: 3
Classifier: Programming Language :: Python :: 3.9
Classifier: Programming Language :: Python :: 3.10
Classifier: Programming Language :: Python :: 3.11
Classifier: Programming Language :: Python :: 3.12
Classifier: Programming Language :: Python :: 3.13
Classifier: Topic :: Scientific/Engineering :: Physics
Requires-Dist: Pint (>=0.24.4,<0.25.0)
Requires-Dist: importlib-metadata (>=4.0,<5.0) ; python_version < "3.9"
Requires-Dist: matplotlib (>=3.9.0,<4.0.0)
Requires-Dist: numpy (>=2.0.0,<3.0.0)
Project-URL: Documentation, https://cavcalc.readthedocs.io/en/latest/
Project-URL: Repository, https://gitlab.com/sjrowlinson/cavcalc
